MANIFEST.in
README.rst
setup.py
auslfe/__init__.py
auslfe.formonline.pfgadapter.egg-info/PKG-INFO
auslfe.formonline.pfgadapter.egg-info/SOURCES.txt
auslfe.formonline.pfgadapter.egg-info/dependency_links.txt
auslfe.formonline.pfgadapter.egg-info/entry_points.txt
auslfe.formonline.pfgadapter.egg-info/namespace_packages.txt
auslfe.formonline.pfgadapter.egg-info/not-zip-safe
auslfe.formonline.pfgadapter.egg-info/requires.txt
auslfe.formonline.pfgadapter.egg-info/top_level.txt
auslfe/formonline/__init__.py
auslfe/formonline/pfgadapter/README.txt
auslfe/formonline/pfgadapter/__init__.py
auslfe/formonline/pfgadapter/composer.py
auslfe/formonline/pfgadapter/config.py
auslfe/formonline/pfgadapter/configure.zcml
auslfe/formonline/pfgadapter/i18n.sh
auslfe/formonline/pfgadapter/interfaces.py
auslfe/formonline/pfgadapter/sharing_provider.py
auslfe/formonline/pfgadapter/browser/__init__.py
auslfe/formonline/pfgadapter/browser/check_dependencies.py
auslfe/formonline/pfgadapter/browser/configure.zcml
auslfe/formonline/pfgadapter/browser/formOnlineTextTemplate.pt
auslfe/formonline/pfgadapter/browser/images/dateok.gif
auslfe/formonline/pfgadapter/content/__init__.py
auslfe/formonline/pfgadapter/content/formOnlineAdapter.py
auslfe/formonline/pfgadapter/i18n/plone-formonline-it.po
auslfe/formonline/pfgadapter/i18n/plone-formonline.pot
auslfe/formonline/pfgadapter/i18n/plone-manual.pot
auslfe/formonline/pfgadapter/locales/auslfe.formonline.pfgadapter-manual.pot
auslfe/formonline/pfgadapter/locales/auslfe.formonline.pfgadapter.pot
auslfe/formonline/pfgadapter/locales/it/LC_MESSAGES/auslfe.formonline.pfgadapter.mo
auslfe/formonline/pfgadapter/locales/it/LC_MESSAGES/auslfe.formonline.pfgadapter.po
auslfe/formonline/pfgadapter/profiles/default/factorytool.xml
auslfe/formonline/pfgadapter/profiles/default/metadata.xml
auslfe/formonline/pfgadapter/profiles/default/propertiestool.xml
auslfe/formonline/pfgadapter/profiles/default/rolemap.xml
auslfe/formonline/pfgadapter/profiles/default/types.xml
auslfe/formonline/pfgadapter/profiles/default/workflows.xml
auslfe/formonline/pfgadapter/profiles/default/types/FormFolder.xml
auslfe/formonline/pfgadapter/profiles/default/types/FormOnlineAdapter.xml
auslfe/formonline/pfgadapter/tests/__init__.py
auslfe/formonline/pfgadapter/tests/base.py
auslfe/formonline/pfgadapter/tests/test_doctest.py
docs/HISTORY.rst
docs/INSTALL.txt
docs/LICENSE.GPL
docs/LICENSE.txt