Metadata-Version: 1.0
Name: auslfe.formonline.pfgadapter
Version: 0.7.2
Summary: An adapter for PloneFormGen that add to Plone a way for manage online forms submission
Home-page: http://plone.org/products/auslfe.formonline.pfgadapter
Author: RedTurtle Technology
Author-email: sviluppoplone@redturtle.it
License: GPL
Keywords: plonegov form plone
Platform: UNKNOWN
Classifier: Framework :: Plone
Classifier: Framework :: Plone :: 3.3
Classifier: Framework :: Plone :: 4.0
Classifier: Framework :: Plone :: 4.1
Classifier: Framework :: Plone :: 4.2
Classifier: Framework :: Plone :: 4.3
Classifier: Programming Language :: Python
Classifier: Development Status :: 5 - Production/Stable
Classifier: License :: OSI Approved :: GNU General Public License (GPL)
